ovos_PHAL_plugin_gui_network_client/__init__.py
ovos_PHAL_plugin_gui_network_client/version.py
ovos_PHAL_plugin_gui_network_client/locale/ca-es/debug_ap_created.dialog
ovos_PHAL_plugin_gui_network_client/locale/ca-es/debug_ap_start.dialog
ovos_PHAL_plugin_gui_network_client/locale/ca-es/debug_ap_stop.dialog
ovos_PHAL_plugin_gui_network_client/locale/ca-es/debug_ap_stopped.dialog
ovos_PHAL_plugin_gui_network_client/locale/ca-es/debug_connecting.dialog
ovos_PHAL_plugin_gui_network_client/locale/ca-es/debug_end_setup.dialog
ovos_PHAL_plugin_gui_network_client/locale/ca-es/debug_http_started.dialog
ovos_PHAL_plugin_gui_network_client/locale/ca-es/debug_start_setup.dialog
ovos_PHAL_plugin_gui_network_client/locale/ca-es/debug_user_connected.dialog
ovos_PHAL_plugin_gui_network_client/locale/ca-es/debug_wifi_connected.dialog
ovos_PHAL_plugin_gui_network_client/locale/ca-es/debug_wifi_error.dialog
ovos_PHAL_plugin_gui_network_client/locale/ca-es/debug_wifi_scanned.dialog
ovos_PHAL_plugin_gui_network_client/locale/ca-es/launch_setup.intent
ovos_PHAL_plugin_gui_network_client/locale/ca-es/wifi_intro.dialog
ovos_PHAL_plugin_gui_network_client/locale/en-us/debug_ap_created.dialog
ovos_PHAL_plugin_gui_network_client/locale/en-us/debug_ap_start.dialog
ovos_PHAL_plugin_gui_network_client/locale/en-us/debug_ap_stop.dialog
ovos_PHAL_plugin_gui_network_client/locale/en-us/debug_ap_stopped.dialog
ovos_PHAL_plugin_gui_network_client/locale/en-us/debug_connecting.dialog
ovos_PHAL_plugin_gui_network_client/locale/en-us/debug_end_setup.dialog
ovos_PHAL_plugin_gui_network_client/locale/en-us/debug_http_started.dialog
ovos_PHAL_plugin_gui_network_client/locale/en-us/debug_start_setup.dialog
ovos_PHAL_plugin_gui_network_client/locale/en-us/debug_user_connected.dialog
ovos_PHAL_plugin_gui_network_client/locale/en-us/debug_wifi_connected.dialog
ovos_PHAL_plugin_gui_network_client/locale/en-us/debug_wifi_error.dialog
ovos_PHAL_plugin_gui_network_client/locale/en-us/debug_wifi_scanned.dialog
ovos_PHAL_plugin_gui_network_client-0.0.2.dist-info/LICENSE
ovos_PHAL_plugin_gui_network_client-0.0.2.dist-info/METADATA
ovos_PHAL_plugin_gui_network_client-0.0.2.dist-info/WHEEL
ovos_PHAL_plugin_gui_network_client-0.0.2.dist-info/entry_points.txt
ovos_PHAL_plugin_gui_network_client-0.0.2.dist-info/top_level.txt
ovos_PHAL_plugin_gui_network_client-0.0.2.dist-info/zip-safe
ovos_PHAL_plugin_gui_network_client-0.0.2.dist-info/RECORD
